{"cameraMode":{"drawMode":0,"name":"Shaded","section":"Shading Mode"},"sceneLighting":true,"audioPlay":false,"sceneViewState":{"showFog":true,"showMaterialUpdate":false,"showSkybox":true,"showFlares":true,"showImageEffects":true,"showParticleSystems":true,"showVisualEffectGraphs":true,"m_FxEnabled":true},"in2DMode":false,"pivot":{"x":1.4778025150299073,"y":3.1849396228790285,"z":0.782689094543457},"rotation":{"x":-0.08330080658197403,"y":0.7629559636116028,"z":-0.10037416964769364,"w":-0.6331644058227539},"size":1.1660256385803223,"orthographic":false}