{"cameraMode":{"drawMode":0,"name":"Shaded","section":"Shading Mode"},"sceneLighting":true,"audioPlay":false,"sceneViewState":{"showFog":true,"showMaterialUpdate":false,"showSkybox":true,"showFlares":true,"showImageEffects":true,"showParticleSystems":true,"showVisualEffectGraphs":true,"m_FxEnabled":true},"in2DMode":false,"pivot":{"x":48.37155532836914,"y":9.448596954345704,"z":28.646102905273439},"rotation":{"x":-0.2873097062110901,"y":-0.6206973791122437,"z":0.26191452145576479,"w":-0.6808773875236511},"size":1.65277099609375,"orthographic":false}